Workbook

Sheet README
A1: Project | B1: Purpose | C1: Rows | D1: Date Range
A2: Sales Analysis Dashboard | B2: Practice dataset for Excel, SQL and Power BI | C2: 1200 | D2: 2024-01-01 to 2025-12-30

Sheet Sales_Data
A1: Order_ID | B1: Order_Date | C1: Customer_Name | D1: Category | E1: Sub_Category | F1: Product_Name | G1: Region | H1: State | I1: Sales | J1: Quantity | K1: Discount | L1: Profit | M1: Payment_Mode | N1: Year | O1: Month
A2: ORD10001 | B2: 45324 | C2: Aarav Sharma | D2: Office Supplies | E2: Paper | F2: Premium Paper | G2: North | H2: Haryana | I2: 9332 | J2: 4 | K2: 0 | L2: 1848.66 | M2: UPI | N2: =YEAR(B2) -> 2024 | O2: =TEXT(B2,"mmmm") -> February
A3: ORD10002 | B3: 45455 | C3: Rohan Khan | D3: Technology | E3: Smartphones | F3: Basic Smartphones | G3: North | H3: Punjab | I3: 109522 | J3: 7 | K3: 0 | L3: 25382.98 | M3: Debit Card | N3: =YEAR(B3) -> 2024 | O3: =TEXT(B3,"mmmm") -> June
A4: ORD10003 | B4: 45336 | C4: Neha Yadav | D4: Furniture | E4: Desks | F4: Premium Desks | G4: South | H4: Telangana | I4: 7144.2 | J4: 2 | K4: 0.1 | L4: 1255.56 | M4: Net Banking | N4: =YEAR(B4) -> 2024 | O4: =TEXT(B4,"mmmm") -> February
A5: ORD10004 | B5: 45588 | C5: Priya Singh | D5: Technology | E5: Keyboards | F5: Basic Keyboards | G5: North | H5: Haryana | I5: 234222 | J5: 6 | K5: 0 | L5: 49714.24 | M5: Credit Card | N5: =YEAR(B5) -> 2024 | O5: =TEXT(B5,"mmmm") -> October
A6: ORD10005 | B6: 46010 | C6: Priya Singh | D6: Technology | E6: Keyboards | F6: Basic Keyboards | G6: East | H6: Jharkhand | I6: 67596.3 | J6: 6 | K6: 0.05 | L6: 13623.02 | M6: Net Banking | N6: =YEAR(B6) -> 2025 | O6: =TEXT(B6,"mmmm") -> December
A7: ORD10006 | B7: 45324 | C7: Sneha Joshi | D7: Office Supplies | E7: Binders | F7: Standard Binders | G7: South | H7: Tamil Nadu | I7: 9996 | J7: 7 | K7: 0 | L7: 1257.59 | M7: Cash | N7: =YEAR(B7) -> 2024 | O7: =TEXT(B7,"mmmm") -> February
A8: ORD10007 | B8: 45866 | C8: Aditya Mehta | D8: Furniture | E8: Chairs | F8: Premium Chairs | G8: South | H8: Telangana | I8: 114012 | J8: 8 | K8: 0.1 | L8: 9454.57 | M8: Debit Card | N8: =YEAR(B8) -> 2025 | O8: =TEXT(B8,"mmmm") -> July
A9: ORD10008 | B9: 45404 | C9: Rahul Verma | D9: Office Supplies | E9: Storage Boxes | F9: Standard Storage Boxes | G9: West | H9: Goa | I9: 8484 | J9: 4 | K9: 0 | L9: 1961.13 | M9: Credit Card | N9: =YEAR(B9) -> 2024 | O9: =TEXT(B9,"mmmm") -> April
A10: ORD10009 | B10: 45409 | C10: Aditya Mehta | D10: Office Supplies | E10: Staplers | F10: Standard Staplers | G10: North | H10: Uttar Pradesh | I10: 18928 | J10: 8 | K10: 0 | L10: 4089.52 | M10: Debit Card | N10: =YEAR(B10) -> 2024 | O10: =TEXT(B10,"mmmm") -> April
A11: ORD10010 | B11: 45811 | C11: Priya Singh | D11: Office Supplies | E11: Pens | F11: Standard Pens | G11: North | H11: Haryana | I11: 2827.2 | J11: 3 | K11: 0.2 | L11: 515.66 | M11: Debit Card | N11: =YEAR(B11) -> 2025 | O11: =TEXT(B11,"mmmm") -> June
A12: ORD10011 | B12: 45663 | C12: Vikram Patel | D12: Office Supplies | E12: Storage Boxes | F12: Standard Storage Boxes | G12: South | H12: Tamil Nadu | I12: 3638.85 | J12: 3 | K12: 0.15 | L12: 168.83 | M12: Credit Card | N12: =YEAR(B12) -> 2025 | O12: =TEXT(B12,"mmmm") -> January
A13: ORD10012 | B13: 45778 | C13: Aditya Mehta | D13: Technology | E13: Smartphones | F13: Basic Smartphones | G13: North | H13: Delhi | I13: 415552.8 | J13: 8 | K13: 0.05 | L13: 38720.5 | M13: Credit Card | N13: =YEAR(B13) -> 2025 | O13: =TEXT(B13,"mmmm") -> May
... A1201: ORD11200 | B1201: 45667 | C1201: Sneha Joshi | D1201: Furniture | E1201: Tables | F1201: Premium Tables | G1201: North | H1201: Punjab | I1201: 6287.1 | J1201: 1 | K1201: 0.05 | L1201: 790.82 | M1201: Net Banking | N1201: =YEAR(B1201) -> 2025 | O1201: =TEXT(B1201,"mmmm") -> January

Sheet Analysis
A1: Sales Analysis
A3: Total Sales | B3: =SUM(Sales_Data!I:I) -> 71404220
A4: Total Profit | B4: =SUM(Sales_Data!L:L) -> 10715237
A5: Total Quantity | B5: =SUM(Sales_Data!J:J) -> 5480
A6: Total Orders | B6: =COUNTA(Sales_Data!A:A)-1 -> 1200
A9: A | B9: B | C9: C
A10: Category | B10: Total Sales | C10: Total Profit
A11: Technology | B11: =SUMIF(Sales_Data!D:D,A11,Sales_Data!I:I) -> 53396510 | C11: =SUMIF(Sales_Data!D:D,A11,Sales_Data!L:L) -> 8003115.8
A12: Furniture | B12: =SUMIF(Sales_Data!D:D,A12,Sales_Data!I:I) -> 15966525 | C12: =SUMIF(Sales_Data!D:D,A12,Sales_Data!L:L) -> 2380824.4
A13: Office Supplies | B13: =SUMIF(Sales_Data!D:D,A13,Sales_Data!I:I) -> 2041184 | C13: =SUMIF(Sales_Data!D:D,A13,Sales_Data!L:L) -> 331297.21
A14: A | B14: B
A15: Profit Margin | B15: =B4/B3 -> 0.15006448
A17: A | B17: B | C17: C
A18: Region | B18: Total Sales | C18: Total Profit
A19: North | B19: =SUMIF(Sales_Data!G:G,A16,Sales_Data!I:I) -> 0 | C19: =SUMIF(Sales_Data!G:G,A16,Sales_Data!L:L) -> 0
A20: South | B20: =SUMIF(Sales_Data!G:G,A17,Sales_Data!I:I) -> 0 | C20: =SUMIF(Sales_Data!G:G,A17,Sales_Data!L:L) -> 0
A21: East | B21: =SUMIF(Sales_Data!G:G,A18,Sales_Data!I:I) -> 0 | C21: =SUMIF(Sales_Data!G:G,A18,Sales_Data!L:L) -> 0
A22: West | B22: =SUMIF(Sales_Data!G:G,A19,Sales_Data!I:I) -> 21731760 | C22: =SUMIF(Sales_Data!G:G,A19,Sales_Data!L:L) -> 2975602.9

Sheet Monthly analysis
A3: Row Labels | B3: Sum of Sales
A4: 2024 | B4: 36297351
A5: January | B5: 3667694.9
A6: February | B6: 2510187.6
A7: March | B7: 2419223
A8: April | B8: 2759890.2
A9: May | B9: 1864093.6
A10: June | B10: 2465048.1
A11: July | B11: 2479254.9
A12: August | B12: 4040262.1
A13: September | B13: 2438921.2
A14: October | B14: 4240651.2
A15: November | B15: 4404915.3
A16: December | B16: 3007209.2
A17: 2025 | B17: 35106868
A18: January | B18: 3793248.2
A19: February | B19: 2123255.8
A20: March | B20: 3224146.5
A21: April | B21: 3188682.2
A22: May | B22: 3300832.4
A23: June | B23: 2138918.2
A24: July | B24: 2420404.7
A25: August | B25: 2542678.4
A26: September | B26: 2948330.6
A27: October | B27: 3434906.3
A28: November | B28: 2380817.2
A29: December | B29: 3610647.9
A30: (blank)
A31: Grand Total | B31: 71404220

Sheet Top 10 Product by Sales
A3: Row Labels | B3: Sum of Sales
A4: Basic Keyboards | B4: 3852843.4
A5: Basic Printers | B5: 3818214
A6: Basic Smartphones | B6: 5379568.5
A7: Premium Monitors | B7: 3605706.8
A8: Premium Printers | B8: 4396670.4
A9: Premium Smartphones | B9: 3644340.7
A10: Standard Keyboards | B10: 3949347.5
A11: Standard Laptops | B11: 3943893.8
A12: Standard Monitors | B12: 3362555.5
A13: Standard Smartphones | B13: 3425700.9
A14: Grand Total | B14: 39378841
